{
  "greeting": "HIII!!",
  "name": "AFIFAH!! ",
  "greetingText": "such a pretty name!",
  "wishText": "happiest birthday to you my other half, hope you are happy and fine, I'm wishing you nothing but happiness with your whole existence!",
  "imagePath": "img/lydia2.png",
  "text1": "HAPPY BIRTHDAYY SAYANG!!! ",
  "textInChatBox": "Happy birthday to you!! Yeee! Many many happy blah..",
  "sendButtonLabel": "KLIKKK",
  "text2": "That's what I was going to do.",
  "text3": "But then I stopped.",
  "text4": "I realised, I wanted to do something",
  "text4Adjective": "special",
  "text5Entry": "Because，",
  "text5Content": "You are Special",
  "smiley": ":D",
  "bigTextPart1": "S",
  "bigTextPart2": "O",
  "wishHeading": "Happy Birthday!",
  "outroText": "Okay, now come back and tell me if you liked it.",
  "replayText": "Or click, if you want to watch it again.",
  "outroSmiley": ":)"
}